{
  "name": "Leona Luna",
  "age": 46,
  "address": {
    "street": "Sublo Avenue",
    "city": "Ojzektuk",
    "state": "NH",
    "zip": "74731"
  },
  "contact": {
    "phone": "(241) 339-8820",
    "servicePhone": "800447836"
  },
  "birthday": "1977-08-04T12:26:39.852Z",
  "ip": "216.154.242.91",
  "foo": "bar",
  "profile": {
    "about": "Nushejro co odapede icoga olko funipe rumfof dij heb medup zus sipemco niv roropro. Wa sipnujor veg tusadazez ka padsavu jube popijub hu wiv po zelowid bim wifave. Bam viz hutkoupo godleskuv bojlaloc ziod cem jul lahcu vi ma lufib fasfu fasrakki dujitu kifodok rok. Muhgulup mupaz ishecec pufu aluus apopas wag zovopi rizami pu ubakoclak kawkamraf eze toude. Dicvo rel pizku pebibus vitzehjow viczad es vekemaj cohi cik gaz tihbu rucarmow rucoreasa beg owulimsef wowecik te. Pe gackoczop ejaizu uso ser ramhofon totrub gelkev ave hi kiof fidhaj.",
    "bio": "Ne fe uf lo ubvibed fervimaj ehahog makew woprow na ewiha ki zivin uzu uzkumak sud joz. Akuagojil limukse et sa is vil ta wosukni bodcel ni johhihta mi unozu natfa ziz. Lop lij ono gaubo weje zufvovve nackekwo gel icate nesenrad osoeke atouji pewo iwaosci som wadajno rucuuse onsab. Ihe uroevogo ebzag hobu enu capcud huringim pobe tejhi uji ogefona va din ono azeelfo waloculu bikwe."
  },
  "apiKey": "81c07b62d8a59447596b33926e709f84c6bc1876ea995662556666b03cc1fb50",
  "currency": {
    "code": "THB",
    "name": "Thailand Baht"
  }
}