{
  "name": "Hallie Day",
  "age": 31,
  "address": {
    "street": "Odolim Place",
    "city": "Rurujci",
    "state": "AZ",
    "zip": "09689"
  },
  "contact": {
    "phone": "(276) 382-2615",
    "servicePhone": "800858281"
  },
  "birthday": "2003-08-07T13:48:42.486Z",
  "ip": "174.191.136.167",
  "foo": "bar",
  "profile": {
    "about": "Gegiw ko jopbe idatap idesoeco ro vuovra fohsuro hongozec waav gacedkov gobufum vehzotza la widfu. Cabarabu meda rup noof ri be cetsucev urudetil fe osujtaw wivjuki lapwijef. Ew man sepe tud ja adera bohop okkav ahupupun ujuokicir eweowu cabojce net subo uzi monnuze.",
    "bio": "Nu upiape ud umcin veasiheh tiitja tuhru hejes kaf dehisde pelomvav tabafe imu efutaub letev ejehal. Bulinwu tirjipih kuapnec haticuj dobro luci banu heme su zubnizi wahsozawi dehulka izagavaja haufcag iwdihoj velec. Ebe siwtuaje ma maj an jusmu uwasi ek beefuso cu gilsen peeme ruwevozuf lec avu habgi kejga ekaid. Eguudawes varoum saznojke pebfu sivda makadan wadpuhwi huwaz ijadewic dasjeg ahezegu acasehbic avual bunilla kugo se. Suk ilahosum lu semsal pawvuf ri nabowsur ca od ramdaf rapavik se rifba sa tovhon soro ku agoeweko. Koblu hihiwju egradu vokepcu ti pelolap gefkemked ji boonzud labwa ko iralap lodirusi saimuku jo. Coh boaj du janeg ce halwuwlih nobmubzok ine adva fenurde wa ihvi."
  },
  "apiKey": "b71a86beb91ea9b1e59e7f244c8964e252a01c1af95f3a91d64658c5c4f4f1e7",
  "currency": {
    "code": "RON",
    "name": "Romania New Leu"
  }
}