{
  "name": "Ray Lyons",
  "age": 38,
  "address": {
    "street": "Nugkav Trail",
    "city": "Niwcemkic",
    "state": "WA",
    "zip": "90980"
  },
  "contact": {
    "phone": "(753) 349-6565",
    "servicePhone": "800292677"
  },
  "birthday": "2006-05-04T08:38:30.411Z",
  "ip": "247.161.113.216",
  "foo": "bar",
  "profile": {
    "about": "Raz doctazda osgirega vovaw oka vuk wi rikozeudu baw ezdal duhacdoj napteg siluz ori luew wifpiv he. Deb omluso vozecsot juppez cetdab icaeji fig se folu sa tejefe kutleku. Sadike leg mom vujlit vasu sehuoz hekcorude dicut ofaavec mebvupza ipkan ze jicfoza nassodaj. Sihiil irki ha pinsok ufkoga nop ta mus moh ewa hiti teg te fo ur. Rav fuge enruh zapam huomi hufa rufdumer jumhes oji necsezo seucbic pug les.",
    "bio": "Pita gucerme paod laamlov afnuek kaawitid luzripbet ida sapemja kak weromjar hotu gavbujes it iwiinre ire. Divlu ru nubkis se kajhaluh jenika je lufgecuju rizeeda fa af mujnovjok narwof. Usjan ma ub uv ziv mir jorsi wulka at zik gewegdov sut ekivefed kivuzfah zi lol isa. Rutucdow fiiw jos eme tol gukim lobejpin ha haadu jij fev zucemhor diszob jatpiz midnedcop. Uvjaf cutetmo uwojuje teghuf nopzawpub net rizmije zevwo loz bulutub du cil jowroduca ta witvadruc jeniz cavihogop. Faznov besna dikec mod hegebre keveseh sikeete nuvafe begra ajacekuje buw lalag jig sa punufre git. Tup fi si ikulorme fawcujav rafok gog geja ronpif fuhot tu gal jurfuka ce asihogaf nimunefe tavnewof ma."
  },
  "apiKey": "e1edbc6335f3d171ee1399bcc7ad901c8f555c9fb85e61e2ecee8b936eee424f",
  "currency": {
    "code": "MUR",
    "name": "Mauritius Rupee"
  }
}